link_traits/__init__.py
link_traits/link_traits.py
link_traits/test_link_traits.py
link_traits-1.0.2.dist-info/DESCRIPTION.rst
link_traits-1.0.2.dist-info/METADATA
link_traits-1.0.2.dist-info/RECORD
link_traits-1.0.2.dist-info/WHEEL
link_traits-1.0.2.dist-info/metadata.json
link_traits-1.0.2.dist-info/top_level.txt
