Metadata-Version: 2.0
Name: link-traits
Version: 1.0.2
Summary: A fork to traitlets' link and dlink to link traits in addition to traitlets.
Home-page: https://github.com/hyperspy/link_traits
Author: The HyperSpy Developers
Author-email: devel@hyperspy.org
License: BSD-3-Clause
Keywords: traits traitlets ipywidgets traitsui
Platform: UNKNOWN
Classifier: Development Status :: 5 - Production/Stable
Classifier: Intended Audience :: Developers
Classifier: Topic :: Software Development :: Build Tools
Classifier: License :: OSI Approved :: BSD License
Classifier: Programming Language :: Python :: 3
Requires-Dist: traits
Provides-Extra: test
Requires-Dist: pytest; extra == 'test'
